[
    {"turkish": "mevsim", "russian": "время года"},
    {"turkish": "ilkbahar", "russian": "весна"},
    {"turkish": "yaz", "russian": "лето"},
    {"turkish": "sonbahar", "russian": "осень"},
    {"turkish": "kış", "russian": "зима"},
    {"turkish": "ocak", "russian": "январь"},
    {"turkish": "şubat", "russian": "февраль"},
    {"turkish": "mart", "russian": "март"},
    {"turkish": "nisan", "russian": "апрель"},
    {"turkish": "mayıs", "russian": "май"},
    {"turkish": "haziran", "russian": "июнь"},
    {"turkish": "temmuz", "russian": "июль"},
    {"turkish": "ağustos", "russian": "август"},
    {"turkish": "eylül", "russian": "сентябрь"},
    {"turkish": "ekim", "russian": "октябрь"},
    {"turkish": "kasım", "russian": "ноябрь"},
    {"turkish": "aralık", "russian": "декабрь"},
    {"turkish": "pazartesi", "russian": "понедельник"},
    {"turkish": "salı", "russian": "вторник"},
    {"turkish": "çarşamba", "russian": "среда"},
    {"turkish": "perşembe", "russian": "четверг"},
    {"turkish": "cuma", "russian": "пятница"},
    {"turkish": "cumartesi", "russian": "суббота"},
    {"turkish": "pazar", "russian": "воскресенье"},
    {"turkish": "sabah", "russian": "утро"},
    {"turkish": "öğle", "russian": "день"},
    {"turkish": "akşam", "russian": "вечер"},
    {"turkish": "gece", "russian": "ночь"},
    {"turkish": "dün", "russian": "вчера"},
    {"turkish": "bugün", "russian": "сегодня"},
    {"turkish": "yarın", "russian": "завтра"},
    {"turkish": "hafta", "russian": "неделя"},
    {"turkish": "ay", "russian": "месяц"},
    {"turkish": "yıl", "russian": "год"},
    {"turkish": "asır", "russian": "век"},
    {"turkish": "mevsimler nasıl?", "russian": "Какие бывают времена года?"},
    {"turkish": "Şu an hangi mevsimdeyiz?", "russian": "Какое сейчас время года?"},
    {"turkish": "En sevdiğin mevsim hangisi?", "russian": "Какое твое любимое время года?"},
    {"turkish": "Hangi aydayız?", "russian": "Какой сейчас месяц?"},
    {"turkish": "Doğum günün hangi ayda?", "russian": "В каком месяце твой день рождения?"},
    {"turkish": "Bu hafta sonu ne yapacaksın?", "russian": "Что ты будешь делать на этих выходных?"},
    {"turkish": "Haftanın ilk günü hangisi?", "russian": "Какой первый день недели?"},
    {"turkish": "Tatil ne zaman başlıyor?", "russian": "Когда начинаются каникулы?"},
    {"turkish": "Saat kaç?", "russian": "Который час?"},
    {"turkish": "Sabah kaçta kalkıyorsun?", "russian": "Во сколько ты встаешь утром?"},
    {"turkish": "Akşam yemeği saati ne zaman?", "russian": "Когда время ужина?"},
    {"turkish": "Randevum saat üçte", "russian": "У меня встреча в три часа"},
    {"turkish": "Yarım saat sonra görüşelim", "russian": "Встретимся через полчаса"},
    {"turkish": "Gece yarısı", "russian": "полночь"},
    {"turkish": "Öğle vakti", "russian": "полдень"},
    {"turkish": "Zaman nasıl geçiyor?", "russian": "Как проходит время?"},
    {"turkish": "Takvime bakabilir miyim?", "russian": "Можно посмотреть календарь?"},
    {"turkish": "Bu ay kaç gün var?", "russian": "Сколько дней в этом месяце?"},
    {"turkish": "Artık yıl nedir?", "russian": "Что такое високосный год?"},
    {"turkish": "Hafta içi", "russian": "будни"},
    {"turkish": "Hafta sonu", "russian": "выходные"},
    {"turkish": "Bayram", "russian": "праздник"},
    {"turkish": "Yılbaşı", "russian": "Новый год"},
    {"turkish": "Noel", "russian": "Рождество"},
    {"turkish": "Paskalya", "russian": "Пасха"},
    {"turkish": "Doğum günü", "russian": "день рождения"},
    {"turkish": "Yıldönümü", "russian": "годовщина"},
    {"turkish": "Takvim yaprağı", "russian": "листок календаря"},
    {"turkish": "Zaman dilimi", "russian": "часовой пояс"},
    {"turkish": "Saat farkı", "russian": "разница во времени"},
    {"turkish": "Kronometre", "russian": "секундомер"},
    {"turkish": "Çeyrek geçiyor", "russian": "четверть первого"},
    {"turkish": "Bu yaz ne yapacaksın?", "russian": "Что ты будешь делать этим летом?"},
    {"turkish": "Sonbaharda yağmur yağar", "russian": "Осенью идет дождь"},
    {"turkish": "Kışın kar yağar", "russian": "Зимой идет снег"},
    {"turkish": "İlkbahar temizliği", "russian": "весенняя уборка"},
    {"turkish": "Yaz tatili", "russian": "летние каникулы"},
    {"turkish": "Takvim yaprağını koparmak", "russian": "оторвать листок календаря"},
    {"turkish": "Zaman yönetimi", "russian": "управление временем"},
    {"turkish": "Vakit nakittir", "russian": "время — деньги"},
    {"turkish": "Geç kaldım", "russian": "Я опоздал"},
    {"turkish": "Erken geldim", "russian": "Я пришел рано"},
    {"turkish": "Zaman yetmedi", "russian": "Времени не хватило"},
    {"turkish": "Süre doldu", "russian": "Время вышло"},
    {"turkish": "An itibarıyla", "russian": "в данный момент"},
    {"turkish": "Gelecek hafta", "russian": "на следующей неделе"},
    {"turkish": "Geçen ay", "russian": "в прошлом месяце"},
    {"turkish": "Önümüzdeki yıl", "russian": "в следующем году"},
    {"turkish": "Bir dakika", "russian": "одна минута"},
    {"turkish": "Bir saat", "russian": "один час"},
    {"turkish": "Bir hafta", "russian": "одна неделя"},
    {"turkish": "Bir ay", "russian": "один месяц"},
    {"turkish": "Bir yüzyıl", "russian": "один век"},
    {"turkish": "Şafak vakti", "russian": "рассвет"},
    {"turkish": "Gün batımı", "russian": "закат"},
    {"turkish": "Öğleden sonra", "russian": "после полудня"},
    {"turkish": "Gece yarısından sonra", "russian": "после полуночи"},
    {"turkish": "Haftanın günleri", "russian": "дни недели"},
    {"turkish": "Ayın ilk günü", "russian": "первый день месяца"},
    {"turkish": "Ayın son günü", "russian": "последний день месяца"},
    {"turkish": "Yaz saati uygulaması", "russian": "летнее время"},
    {"turkish": "Kış saati uygulaması", "russian": "зимнее время"},
    {"turkish": "Takvimi işaretle", "russian": "отметь в календаре"},
    {"turkish": "Zaman çizelgesi", "russian": "расписание"},
    {"turkish": "Kronolojik sıra", "russian": "хронологический порядок"},
    {"turkish": "Yıllık plan", "russian": "годовой план"},
    {"turkish": "Mevsimsel değişiklikler", "russian": "сезонные изменения"},
    {"turkish": "Gün ışığı", "russian": "дневной свет"},
    {"turkish": "Gece karanlığı", "russian": "ночная тьма"},
    {"turkish": "Zaman makinesi", "russian": "машина времени"},
    {"turkish": "Anılar", "russian": "воспоминания"},
    {"turkish": "Gelecek", "russian": "будущее"},
    {"turkish": "Geçmiş", "russian": "прошлое"},
    {"turkish": "Şimdi", "russian": "сейчас"}
  ]